LICENSE.txt
MANIFEST.in
README.rst
setup.py
fix_yahoo_finance/__init__.py
fix_yahoo_finance.egg-info/PKG-INFO
fix_yahoo_finance.egg-info/SOURCES.txt
fix_yahoo_finance.egg-info/dependency_links.txt
fix_yahoo_finance.egg-info/entry_points.txt
fix_yahoo_finance.egg-info/requires.txt
fix_yahoo_finance.egg-info/top_level.txt