Metadata-Version: 1.1
Name: fix-yahoo-finance
Version: 0.0.21
Summary: Fix for Pandas Datareader's get_data_yahoo()
Home-page: https://github.com/ranaroussi/fix-yahoo-finance
Author: Ran Aroussi
Author-email: ran@aroussi.com
License: LGPL
Keywords: pandas,yahoo finance,pandas datareader
Platform: any
Classifier: License :: OSI Approved :: GNU Lesser General Public License v3 (LGPLv3)
Classifier: Development Status :: 3 - Alpha
Classifier: Operating System :: OS Independent
Classifier: Intended Audience :: Developers
Classifier: Topic :: Office/Business :: Financial
Classifier: Topic :: Office/Business :: Financial :: Investment
Classifier: Topic :: Scientific/Engineering :: Interface Engine/Protocol Translator
Classifier: Topic :: Software Development :: Libraries
Classifier: Topic :: Software Development :: Libraries :: Python Modules
Classifier: Programming Language :: Python :: 2.7
Classifier: Programming Language :: Python :: 3.4
Classifier: Programming Language :: Python :: 3.5
Classifier: Programming Language :: Python :: 3.6
